{
  "$schema": "https://developer.microsoft.com/json-schemas/fabric/item/report/definition/visualContainer/2.5.0/schema.json",
  "name": "d1b2c3d4e5f6a7b8c9d2",
  "position": {
    "x": 854,
    "y": 62,
    "width": 426,
    "height": 72
  },
  "visual": {
    "visualType": "card",
    "query": {
      "queryState": {
        "Values": {
          "projections": [
            {
              "field": {
                "Measure": {
                  "Expression": {
                    "SourceRef": {
                      "Entity": "Orders"
                    }
                  },
                  "Property": "Order Revenue"
                }
              },
              "queryRef": "Orders.Order Revenue",
              "active": true
            }
          ]
        }
      }
    },
    "objects": {
      "title": [
        {
          "properties": {
            "text": {
              "expr": {
                "Literal": {
                  "Value": "'Total Book Revenue'"
                }
              }
            }
          }
        }
      ]
    },
    "drillFilterOtherVisuals": true
  }
}